{
	"configurations" : 
	[
		{
			"directories" : 
			[
				{
					"build" : ".",
					"hasInstallRule" : true,
					"jsonFile" : "directory-.-Debug-f072125cf10fa164edaf.json",
					"minimumCMakeVersion" : 
					{
						"string" : "3.16"
					},
					"projectIndex" : 0,
					"source" : ".",
					"targetIndexes" : 
					[
						0,
						1,
						2
					]
				}
			],
			"name" : "Debug",
			"projects" : 
			[
				{
					"directoryIndexes" : 
					[
						0
					],
					"name" : "Chat",
					"targetIndexes" : 
					[
						0,
						1,
						2
					]
				}
			],
			"targets" : 
			[
				{
					"directoryIndex" : 0,
					"id" : "Chat::@6890427a1f51a3e7e1df",
					"jsonFile" : "target-Chat-Debug-7b1f34733416601caa87.json",
					"name" : "Chat",
					"projectIndex" : 0
				},
				{
					"directoryIndex" : 0,
					"id" : "Chat_autogen::@6890427a1f51a3e7e1df",
					"jsonFile" : "target-Chat_autogen-Debug-7b5e09ad8bfc21fb8b62.json",
					"name" : "Chat_autogen",
					"projectIndex" : 0
				},
				{
					"directoryIndex" : 0,
					"id" : "Chat_autogen_timestamp_deps::@6890427a1f51a3e7e1df",
					"jsonFile" : "target-Chat_autogen_timestamp_deps-Debug-9c8d5e31de0310169781.json",
					"name" : "Chat_autogen_timestamp_deps",
					"projectIndex" : 0
				}
			]
		}
	],
	"kind" : "codemodel",
	"paths" : 
	{
		"build" : "C:/c++ projects/Chat/Chat/cmake-build-debug",
		"source" : "C:/c++ projects/Chat/Chat"
	},
	"version" : 
	{
		"major" : 2,
		"minor" : 5
	}
}
